setup.py
aqs_sweeper/__init__.py
aqs_sweeper/tests.py
aqs_sweeper.egg-info/PKG-INFO
aqs_sweeper.egg-info/SOURCES.txt
aqs_sweeper.egg-info/dependency_links.txt
aqs_sweeper.egg-info/entry_points.txt
aqs_sweeper.egg-info/not-zip-safe
aqs_sweeper.egg-info/requires.txt
aqs_sweeper.egg-info/top_level.txt