Metadata-Version: 1.0
Name: aqs-sweeper
Version: 0.1.1
Summary: Extendable Azure Queue Storage dumper that copy your data into Azure Blob Storage.
Home-page: UNKNOWN
Author: Bence Faludi
Author-email: bence@ozmo.hu
License: MIT
Platform: UNKNOWN
